{
  "_generated": "Generated by SweetTooth, do not edit", 
  "description": "Allow to change the output audio device from the volume indicator menu.\n\nThis is a cut-down extension of the Extended Volume indicator without the applications submenu. It's useful to combine the usage with others extensions without having redundancies.\n\nIt allows also to mute/unmute the audio card device; others extensions allows this just only for the applications audio streams.", 
  "name": "Switch output audio devices", 
  "shell-version": [
    "3.4"
  ], 
  "url": "", 
  "uuid": "output-audio-devices@muflone", 
  "version": 2
}